{
    "1013": { "CORE": "001", "IBS": "" , "descTH": "พนักงานบริษัท", "descENG": ""},
    "1051": { "CORE": "002", "IBS": "" , "descTH": "ข้าราชการ", "descENG": ""},
    "1053": { "CORE": "003", "IBS": "" , "descTH": "รัฐวิสาหกิจ", "descENG": ""},
    "2024": { "CORE": "004", "IBS": "" , "descTH": "รับจ้าง", "descENG": ""},
    "2026": { "CORE": "005", "IBS": "" , "descTH": "กิจการส่วนตัว", "descENG": ""},
    "2025": { "CORE": "006", "IBS": "" , "descTH": "ค้าขาย", "descENG": ""},
    "1064": { "CORE": "007", "IBS": "" , "descTH": "นักเรียน", "descENG": ""},
    "1064-x": { "CORE": "008", "IBS": "" , "descTH": "นักศึกษา", "descENG": ""},
    "1056": { "CORE": "009", "IBS": "" , "descTH": "ครู/อาจารย์", "descENG": ""},
    "4053": { "CORE": "010", "IBS": "" , "descTH": "ตำรวจ", "descENG": ""},
    "4053-x": { "CORE": "011", "IBS": "" , "descTH": "ทหาร", "descENG": ""},
    "4001": { "CORE": "012", "IBS": "" , "descTH": "แพทย์", "descENG": ""},
    "4005": { "CORE": "013", "IBS": "" , "descTH": "เภสัชกร", "descENG": ""},
    "2002": { "CORE": "014", "IBS": "" , "descTH": "สถาปนิก", "descENG": ""},
    "1028": { "CORE": "015", "IBS": "" , "descTH": "ทนายความ", "descENG": ""},
    "5010": { "CORE": "016", "IBS": "" , "descTH": "มัคคุเทศน์", "descENG": ""},
    "2006": { "CORE": "017", "IBS": "" , "descTH": "ผู้สื่อข่าว", "descENG": ""},
    "1035": { "CORE": "018", "IBS": "" , "descTH": "นักจัดรายการวิทยุ/โทรทัศน์", "descENG": ""},
    "1042": { "CORE": "019", "IBS": "" , "descTH": "นักประชาสัมพันธ์/หนังสือ", "descENG": ""},
    "4042": { "CORE": "020", "IBS": "" , "descTH": "ช่าง", "descENG": ""},
    "5008": { "CORE": "021", "IBS": "" , "descTH": "คอมพิวเตอร์", "descENG": ""},
    "5014": { "CORE": "022", "IBS": "" , "descTH": "พระ", "descENG": ""},
    "5016": { "CORE": "023", "IBS": "" , "descTH": "แม่ชี", "descENG": ""},
    "1063": { "CORE": "024", "IBS": "" , "descTH": "แม่บ้าน", "descENG": ""},
    "4017": { "CORE": "025", "IBS": "" , "descTH": "เกษตรกร", "descENG": ""},
    "1055": { "CORE": "026", "IBS": "" , "descTH": "หัวหน้าแผนกซ่อมบำรุง", "descENG": ""},
    "1063-x": { "CORE": "027", "IBS": "" , "descTH": "พ่อบ้าน", "descENG": ""},
    "1032": { "CORE": "028", "IBS": "" , "descTH": "บรรณาธิการ", "descENG": ""},
    "029": { "CORE": "029", "IBS": "" , "descTH": "ค้าวัสดุก่อสร้าง", "descENG": ""},
    "4020": { "CORE": "030", "IBS": "" , "descTH": "นักเดินเรือ", "descENG": ""},
    "5013": { "CORE": "031", "IBS": "" , "descTH": "เจ้าหน้าที่ดูแลนักกีฬา", "descENG": ""},
    "4006": { "CORE": "032", "IBS": "" , "descTH": "พยาบาล", "descENG": ""},
    "4055": { "CORE": "033", "IBS": "" , "descTH": "ก่อนวัยเรียน", "descENG": ""},
    "034": { "CORE": "034", "IBS": "" , "descTH": "", "descENG": ""},
    "035": { "CORE": "035", "IBS": "" , "descTH": "", "descENG": ""},
    "036": { "CORE": "036", "IBS": "" , "descTH": "", "descENG": ""},
    "037": { "CORE": "037", "IBS": "" , "descTH": "", "descENG": ""},
    "038": { "CORE": "038", "IBS": "" , "descTH": "", "descENG": ""},
    "039": { "CORE": "039", "IBS": "" , "descTH": "", "descENG": ""},
    "040": { "CORE": "040", "IBS": "" , "descTH": "", "descENG": ""},
    "041": { "CORE": "041", "IBS": "" , "descTH": "", "descENG": ""},
    "042": { "CORE": "042", "IBS": "" , "descTH": "", "descENG": ""},
    "043": { "CORE": "043", "IBS": "" , "descTH": "", "descENG": ""},
    "044": { "CORE": "044", "IBS": "" , "descTH": "", "descENG": ""},
    "045": { "CORE": "045", "IBS": "" , "descTH": "", "descENG": ""},
    "046": { "CORE": "046", "IBS": "" , "descTH": "", "descENG": ""},
    "047": { "CORE": "047", "IBS": "" , "descTH": "", "descENG": ""},
    "048": { "CORE": "048", "IBS": "" , "descTH": "", "descENG": ""},
    "049": { "CORE": "049", "IBS": "" , "descTH": "", "descENG": ""},
    "050": { "CORE": "050", "IBS": "" , "descTH": "", "descENG": ""},
    "051": { "CORE": "051", "IBS": "" , "descTH": "", "descENG": ""},
    "052": { "CORE": "052", "IBS": "" , "descTH": "", "descENG": ""},
    "053": { "CORE": "053", "IBS": "" , "descTH": "", "descENG": ""},
    "054": { "CORE": "054", "IBS": "" , "descTH": "", "descENG": ""},
    "055": { "CORE": "055", "IBS": "" , "descTH": "", "descENG": ""},
    "056": { "CORE": "056", "IBS": "" , "descTH": "", "descENG": ""},
    "057": { "CORE": "057", "IBS": "" , "descTH": "", "descENG": ""},
    "058": { "CORE": "058", "IBS": "" , "descTH": "", "descENG": ""},
    "059": { "CORE": "059", "IBS": "" , "descTH": "", "descENG": ""},
    "060": { "CORE": "060", "IBS": "" , "descTH": "", "descENG": ""},
    "061": { "CORE": "061", "IBS": "" , "descTH": "", "descENG": ""},
    "062": { "CORE": "062", "IBS": "" , "descTH": "", "descENG": ""}

}